DotIndex/__init__.py
DotIndex-1.1.0.dist-info/LICENSE
DotIndex-1.1.0.dist-info/METADATA
DotIndex-1.1.0.dist-info/WHEEL
DotIndex-1.1.0.dist-info/top_level.txt
DotIndex-1.1.0.dist-info/RECORD
