Metadata-Version: 2.1
Name: DotIndex
Version: 1.1.0
Summary: Allows you to use dot notation to index dicts, like how you can in javascript
Author-email: Hazel <trinkey@duck.com>
Project-URL: Homepage, https://github.com/trinkey/dotindex
Project-URL: Issues, https://github.com/trinkey/dotindex/issues
Classifier: Programming Language :: Python :: 3
Classifier: License :: OSI Approved :: GNU Affero General Public License v3
Classifier: Operating System :: OS Independent
Requires-Python: >=3.6
License-File: LICENSE
